botele/__init__.py
botele/botele.py
botele/botlib/__init__.py
botele/botlib/botlib.py
botele/cli/__init__.py
botele/cli/cli.py
botele/cli/install.py
botele/cli/list.py
botele/cli/make.py
botele/cli/run.py
botele/cli/setup.py
botele/filters/__init__.py
botele/filters/filters.py
botele-0.1.1.data/data/botele_data/.botele-bots
botele-0.1.1.data/data/botele_data/.botele-config
botele-0.1.1.data/scripts/botele
botele-0.1.1.dist-info/METADATA
botele-0.1.1.dist-info/WHEEL
botele-0.1.1.dist-info/entry_points.txt
botele-0.1.1.dist-info/top_level.txt
botele-0.1.1.dist-info/RECORD
