Metadata-Version: 2.1
Name: botele
Version: 0.1.1
Summary: Python Telegram Bot Factory
Home-page: https://github.com/pedromxavier/botele
Author: Pedro Maciel Xavier
Author-email: pedromxavier@poli.ufrj.br
License: UNKNOWN
Project-URL: Bug Tracker, https://github.com/pedromxavier/botele/issues
Project-URL: Source, https://github.com/pedromxavier/botele
Platform: UNKNOWN
Classifier: Programming Language :: Python :: 3
Requires-Python: <4,>=3.7
Requires-Dist: lorem
Requires-Dist: python-telegram-bot
Requires-Dist: pyckage (>=0.1.1)
Requires-Dist: cstream (>=1.0.0)
